german_transliterate/core.py
german_transliterate-0.1.3.dist-info/LICENSE
german_transliterate-0.1.3.dist-info/METADATA
german_transliterate-0.1.3.dist-info/WHEEL
german_transliterate-0.1.3.dist-info/top_level.txt
german_transliterate-0.1.3.dist-info/RECORD
